k1a.cpython-310-darwin.so
k1a-1.2.1.dist-info/LICENSE
k1a-1.2.1.dist-info/METADATA
k1a-1.2.1.dist-info/WHEEL
k1a-1.2.1.dist-info/top_level.txt
k1a-1.2.1.dist-info/RECORD
