Metadata-Version: 2.1
Name: k1a
Version: 1.2.1
Summary: Accelerated functionalities for k1lib
Home-page: https://k1a.k1lib.com
Author: Quang Ho
Author-email: 157239q@gmail.com
License: MIT
Platform: UNKNOWN
Requires-Python: >=3.0
License-File: LICENSE
